co_api/__init__.py
co_api/models.py
co_api-0.0.1.dist-info/LICENSE
co_api-0.0.1.dist-info/METADATA
co_api-0.0.1.dist-info/WHEEL
co_api-0.0.1.dist-info/top_level.txt
co_api-0.0.1.dist-info/RECORD
