Metadata-Version: 2.1
Name: co-api
Version: 0.0.1
Summary: Minecraft CoreProtect API
Home-page: https://git.cofob.ru/cofob/co_api
License: UNKNOWN
Platform: UNKNOWN
Requires-Python: >=3.6
License-File: LICENSE
Requires-Dist: mysql-connector-python
